senlib/__init__.py
senlib/__version__.py
senlib/app.py
senlib/cli.py
senlib/mock.py
senlib/mqtt.py
senlib/web.py
senlib/core/__init__.py
senlib/core/i2c.py
senlib/i2c/__init__.py
senlib/i2c/sensors/__init__.py
senlib/i2c/sensors/amx.py
senlib/i2c/sensors/bhx.py
senlib/i2c/sensors/bmex.py
senlib/i2c/sensors/bmpx.py
senlib/i2c/sensors/hdcx.py
senlib/i2c/sensors/lmx.py
senlib/i2c/sensors/mcpx.py
senlib/i2c/sensors/mplx.py
senlib/i2c/sensors/shtx.py
senlib/i2c/sensors/six.py
senlib-0.1.1.dist-info/LICENSE
senlib-0.1.1.dist-info/METADATA
senlib-0.1.1.dist-info/WHEEL
senlib-0.1.1.dist-info/entry_points.txt
senlib-0.1.1.dist-info/top_level.txt
senlib-0.1.1.dist-info/RECORD
