Metadata-Version: 2.1
Name: senlib
Version: 0.1.1
Summary: A pure Python library for some I2C sensors.
Home-page: https://github.com/Awaiskhan404/senlib
Author: Awais khan
Author-email: contact@awaiskhan.com.pk
License: (MIT OR Apache-2.0)
Platform: UNKNOWN
Classifier: Programming Language :: Python
Classifier: Programming Language :: Python :: 3
Classifier: Programming Language :: Python :: 3.3
Classifier: Programming Language :: Python :: 3.4
Classifier: Programming Language :: Python :: 3.5
Classifier: Programming Language :: Python :: 3.6
Requires-Dist: cffi
Requires-Dist: smbus-cffi
Requires-Dist: aiohttp
Requires-Dist: hbmqtt
Requires-Dist: dicttoxml
Requires-Dist: click
